{"commitInfo":{"timestamp":1753599181357,"operation":"WRITE","operationParameters":{"mode":"Overwrite","partitionBy":"[]"},"isolationLevel":"Serializable","isBlindAppend":false,"operationMetrics":{"numFiles":"1","numRemovedFiles":"0","numRemovedBytes":"0","numOutputRows":"0","numOutputBytes":"1049"},"engineInfo":"Apache-Spark/4.0.0 Delta-Lake/4.0.0","txnId":"1dbd54fb-4ccf-4d08-8661-e9b535e3338e"}}
{"metaData":{"id":"51290de0-129d-4b82-bfb3-dc7c21e961d1","format":{"provider":"parquet","options":{}},"schemaString":"{\"type\":\"struct\",\"fields\":[{\"name\":\"Product_HK\",\"type\":\"string\",\"nullable\":true,\"metadata\":{\"__metadata_col\":\"Product_HK\"}},{\"name\":\"product_name\",\"type\":\"string\",\"nullable\":true,\"metadata\":{}},{\"name\":\"category\",\"type\":\"string\",\"nullable\":true,\"metadata\":{}},{\"name\":\"price\",\"type\":\"string\",\"nullable\":true,\"metadata\":{}},{\"name\":\"Load_Date\",\"type\":\"timestamp\",\"nullable\":true,\"metadata\":{}},{\"name\":\"Record_Source\",\"type\":\"string\",\"nullable\":true,\"metadata\":{}},{\"name\":\"Start_Date\",\"type\":\"timestamp\",\"nullable\":true,\"metadata\":{}},{\"name\":\"End_Date\",\"type\":\"timestamp\",\"nullable\":true,\"metadata\":{}},{\"name\":\"Is_Current\",\"type\":\"boolean\",\"nullable\":true,\"metadata\":{}}]}","partitionColumns":[],"configuration":{},"createdTime":1753599145433}}
{"protocol":{"minReaderVersion":1,"minWriterVersion":2}}
